pycounts_ksr/.DS_Store
pycounts_ksr/__init__.py
pycounts_ksr/plotting.py
pycounts_ksr/pycounts_ksr.py
pycounts_ksr-0.1.0.dist-info/LICENSE
pycounts_ksr-0.1.0.dist-info/METADATA
pycounts_ksr-0.1.0.dist-info/WHEEL
pycounts_ksr-0.1.0.dist-info/RECORD
